curr_get_exchange/__init__.py
curr_get_exchange/get_exchange.py
curr_get_exchange-1.0.0.dist-info/LICENSE
curr_get_exchange-1.0.0.dist-info/METADATA
curr_get_exchange-1.0.0.dist-info/WHEEL
curr_get_exchange-1.0.0.dist-info/top_level.txt
curr_get_exchange-1.0.0.dist-info/RECORD
