Metadata-Version: 2.1
Name: curr-get-exchange
Version: 1.0.0
Summary: Get Exchange Rate Between Different Currencies
Home-page: https://github.com/Jullies/Get-Exchange-Rate-Programatically
Author: Jullies Onyango
Author-email: Julliesnyash@gmail.com
License: UNKNOWN
Project-URL: Bug Tracker, https://github.com/Jullies/Get-Exchange-Rate-Programatically/issues
Platform: UNKNOWN
Classifier: Programming Language :: Python :: 3
Classifier: License :: OSI Approved :: MIT License
Classifier: Operating System :: OS Independent
Requires-Python: >=3.6
